kim_property/__init__.py
kim_property/_version.py
kim_property/create.py
kim_property/definition.py
kim_property/destroy.py
kim_property/dump.py
kim_property/ednify.py
kim_property/err.py
kim_property/instance.py
kim_property/modify.py
kim_property/numeric.py
kim_property/remove.py
kim_property/properties/kim_properties.edn
kim_property-2.6.12.dist-info/licenses/LICENSE
kim_property-2.6.12.dist-info/METADATA
kim_property-2.6.12.dist-info/WHEEL
kim_property-2.6.12.dist-info/top_level.txt
kim_property-2.6.12.dist-info/RECORD
