Metadata-Version: 2.4
Name: kim-property
Version: 2.6.12
Summary: kim-property - KIM-PROPERTY utility module.
Author-email: Yaser Afshar <ya.afshar@gmail.com>
Maintainer-email: Yaser Afshar <ya.afshar@gmail.com>
Project-URL: Homepage, https://github.com/openkim/kim-property
Project-URL: Issues, https://github.com/openkim/kim-property/issues
Keywords: kim-property
Classifier: Development Status :: 5 - Production/Stable
Classifier: Intended Audience :: Science/Research
Classifier: Topic :: Scientific/Engineering
Classifier: Operating System :: OS Independent
Classifier: License :: OSI Approved :: GNU Lesser General Public License v2 or later (LGPLv2+)
Classifier: Programming Language :: Python :: 3
Requires-Python: >=3.8
License-File: LICENSE
Requires-Dist: kim-edn>1.4.0
Dynamic: license-file
